setup.py
bradk/utils.py
bradk/webscrap.py
bradk.egg-info/PKG-INFO
bradk.egg-info/SOURCES.txt
bradk.egg-info/dependency_links.txt
bradk.egg-info/not-zip-safe
bradk.egg-info/top_level.txt
bradk/finance/__init__.py
bradk/finance/highs_and_lows.py
bradk/finance/historical_data.py
bradk/finance/techindic.py
bradk/model_selection/__init__.py
bradk/model_selection/xgrid_search.py
bradk/neural_networks/__init__.py
bradk/neural_networks/cnn1d_ks20180119.py
bradk/neural_networks/cnn1d_ks20180815.py
bradk/neural_networks/dnn_ks20180118.py
bradk/neural_networks/dnn_ks20180809.py
bradk/neural_networks/dnn_ks_v2020_05_17.py
bradk/neural_networks/dnn_np20171230.py
bradk/neural_networks/dnn_tf20180111.py
bradk/neural_networks/rnn_LSTM_ks20180824.py