Metadata-Version: 1.0
Name: bradk
Version: 0.11.4
Summary: The bradk packages developed by Brad Kim
Home-page: http://github.com/bomsoo-kim/packages
Author: Brad Kim
Author-email: bk2717@columbia.edu
License: MIT
Platform: UNKNOWN
